kitetrader/Kite.py
kitetrader/__init__.py
kitetrader-3.0.3.dist-info/METADATA
kitetrader-3.0.3.dist-info/WHEEL
kitetrader-3.0.3.dist-info/licenses/LICENSE
kitetrader-3.0.3.dist-info/RECORD
