Metadata-Version: 2.3
Name: kitetrader
Version: 3.0.3
Summary: Unofficial Python Client for Zerodha Kite
Project-URL: Homepage, https://github.com/BennyThadikaran/Kite-Trader
Project-URL: Bug Tracker, https://github.com/BennyThadikaran/Kite-Trader/issues
Author: Benny Thadikaran
License-File: LICENSE
Keywords: algo-trading,historical-data,intraday-data,kiteconnect,stock-data,stock-market,zerodha,zerodha-kite
Classifier: License :: OSI Approved :: GNU General Public License v3 (GPLv3)
Classifier: Operating System :: OS Independent
Classifier: Programming Language :: Python :: 3
Requires-Python: >=3.8
Requires-Dist: mthrottle>=0.0.1
Requires-Dist: requests>=2.31.0
